LICENSE
README.md
gaspra/__init__.py
gaspra/changesets.py
gaspra/common.py
gaspra/difflib_benchmark.py
gaspra/dot_dump.py
gaspra/examples.py
gaspra/markup.py
gaspra/merge.py
gaspra/merge_tool.py
gaspra/multiple_strings.py
gaspra/suffix_automaton.py
gaspra/test_helpers/helpers.py
gaspra/tokenizers.py
gaspra/torture_test.py
gaspra/types.py
gaspra/wrappers.py
gaspra-0.1.0a3.dist-info/LICENSE
gaspra-0.1.0a3.dist-info/METADATA
gaspra-0.1.0a3.dist-info/WHEEL
gaspra-0.1.0a3.dist-info/entry_points.txt
gaspra-0.1.0a3.dist-info/RECORD
