Metadata-Version: 2.1
Name: gaspra
Version: 0.1.0a3
Summary: A fast Python tool for searching, diffing, and merging text
Home-page: https://github.com/mawicks/gaspra
License: BSD-3-Clause
Keywords: diff,LCS,merge,search,text-processing
Author: Mark Wicks
Author-email: mawicks@gmail.com
Requires-Python: >=3.10,<4.0
Classifier: Development Status :: 2 - Pre-Alpha
Classifier: Intended Audience :: Developers
Classifier: License :: OSI Approved :: BSD License
Classifier: Natural Language :: English
Classifier: Operating System :: OS Independent
Classifier: Programming Language :: Python
Classifier: Programming Language :: Python :: 3
Classifier: Programming Language :: Python :: 3.10
Classifier: Programming Language :: Python :: 3.11
Classifier: Programming Language :: Python :: 3.12
Classifier: Topic :: Software Development :: Libraries
Classifier: Topic :: Text Processing
Classifier: Topic :: Utilities
Requires-Dist: rich (>=13.7.0,<14.0.0)
Project-URL: Repository, https://github.com/mawicks/gaspra
